Workbook

Sheet 成本
A2: 日期 | B2: 项目编号 | C2: 客户 | D2: 项目经理 | E2: 目的地 | F2: 年量纲 | G2: 生命周期 | H2: 配送方式 | I2: 类别 | J2: 材料分类 | K2: 名称 | L2: 零件号 | M2: 材料 | N2: 产品尺寸 | O2: 材料成本 | P2: 加工费 | Q2: 三项费用 | R2: 运输费 | S2: 包装费 | T2: 托盘费 | U2: 外仓储服务费 | V2: 器具车 | W2: 实验费 | X2: 模具 | Y2: 成本合计 | Z2: 仓储物流服务费 | AA2: QS | AB2: 输出给销售报价成本
A3: 46266 | B3: T12T | C3: 凯华 | D3: 杨克波 | E3: 芜湖 | F3: 50000 | G3: 5 | H3: 直供 | I3: 模切 | J3: PP+PET | K3: 吸音棉 | L3: 403032281AA-2 | M3: 400g/㎡ 10mm双组份吸音棉 | N3: 354*82*10 | O3: =BOM!H2 -> 0.21888 | P3: =工序工时!AB3 -> 0.081481481 | Q3: =(O3+P3)*0.08 -> 0.024028919 | R3: =物流包装!F3 -> 0.020225625 | S3: =物流包装!G3 -> 0.022916667 | T3: 0 | U3: 0 | V3: 0 | W3: 0.02 | X3: =模检具!V2 -> 0.010619469 | Y3: =SUM(O3:X3) -> 0.39815216 | Z3: 0 | AA3: 0 | AB3: =Y3+Z3+AA3 -> 0.39815216 | AC3: =0.354*0.082 -> 0.029028 | AD3: 0.4 | AE3: =AB3/AC3/AD3 -> 34.290354
A4: 46266 | B4: T12T | C4: 凯华 | D4: 杨克波 | E4: 芜湖 | F4: 50000 | G4: 5 | H4: 直供 | I4: 模切 | J4: PP+PET | K4: 吸音棉 | L4: 403032282AA-2 | M4: 400g/㎡ 10mm双组份吸音棉 | N4: 354*82*10 | O4: =BOM!H3 -> 0.21888 | P4: =工序工时!AB4 -> 0.081481481 | Q4: =(O4+P4)*0.08 -> 0.024028919 | R4: =物流包装!F4 -> 0.020225625 | S4: =物流包装!G4 -> 0.022916667 | T4: 0 | U4: 0 | V4: 0 | W4: 0.02 | X4: =模检具!V3 -> 0.010619469 | Y4: =SUM(O4:X4) -> 0.39815216 | Z4: 0 | AA4: 0 | AB4: =Y4+Z4+AA4 -> 0.39815216 | AC4: =0.354*0.082 -> 0.029028 | AD4: 0.4 | AE4: =AB4/AC4/AD4 -> 34.290354
A5: 46266 | B5: T12T | C5: 凯华 | D5: 杨克波 | E5: 芜湖 | F5: 50000 | G5: 5 | H5: 直供 | I5: 模切 | J5: PP+PET | K5: 吸音棉 | L5: 403034543AA-3 | M5: 400g/㎡ 10mm双组份吸音棉 | N5: 403*90*10 | O5: =BOM!H4 -> 0.26537143 | P5: =工序工时!AB5 -> 0.087301587 | Q5: =(O5+P5)*0.08 -> 0.028213841 | R5: =物流包装!F5 -> 0.020225625 | S5: =物流包装!G5 -> 0.022916667 | T5: 0 | U5: 0 | V5: 0 | W5: 0.02 | X5: =模检具!V4 -> 0.010619469 | Y5: =SUM(O5:X5) -> 0.45464862 | Z5: 0 | AA5: 0 | AB5: =Y5+Z5+AA5 -> 0.45464862 | AC5: =0.403*0.09 -> 0.03627 | AD5: 0.4 | AE5: =AB5/AC5/AD5 -> 31.337787
A6: 46266 | B6: T12T | C6: 凯华 | D6: 杨克波 | E6: 芜湖 | F6: 50000 | G6: 5 | H6: 直供 | I6: 模切 | J6: PP+PET | K6: 吸音棉 | L6: 403037026AA-3 | M6: 400g/㎡ 10mm双组份吸音棉 | N6: 403*90*10 | O6: =BOM!H5 -> 0.26537143 | P6: =工序工时!AB6 -> 0.087301587 | Q6: =(O6+P6)*0.08 -> 0.028213841 | R6: =物流包装!F6 -> 0.020225625 | S6: =物流包装!G6 -> 0.022916667 | T6: 0 | U6: 0 | V6: 0 | W6: 0.02 | X6: =模检具!V5 -> 0.010619469 | Y6: =SUM(O6:X6) -> 0.45464862 | Z6: 0 | AA6: 0 | AB6: =Y6+Z6+AA6 -> 0.45464862 | AC6: =0.403*0.09 -> 0.03627 | AD6: 0.4 | AE6: =AB6/AC6/AD6 -> 31.337787
A7: 46266 | B7: T12T | C7: 凯华 | D7: 杨克波 | E7: 芜湖 | F7: 50000 | G7: 5 | H7: 直供 | I7: 模切 | J7: PP+PET | K7: 吸音棉 | L7: 403037030AA-3 | M7: 400g/㎡ 10mm双组份吸音棉 | N7: 403*90*10 | O7: =BOM!H6 -> 0.26537143 | P7: =工序工时!AB7 -> 0.087301587 | Q7: =(O7+P7)*0.08 -> 0.028213841 | R7: =物流包装!F7 -> 0.020225625 | S7: =物流包装!G7 -> 0.022916667 | T7: 0 | U7: 0 | V7: 0 | W7: 0.02 | X7: =模检具!V6 -> 0.010619469 | Y7: =SUM(O7:X7) -> 0.45464862 | Z7: 0 | AA7: 0 | AB7: =Y7+Z7+AA7 -> 0.45464862 | AC7: =0.403*0.09 -> 0.03627 | AD7: 0.4 | AE7: =AB7/AC7/AD7 -> 31.337787
A8: 46266 | B8: T12T | C8: 凯华 | D8: 杨克波 | E8: 芜湖 | F8: 50000 | G8: 5 | H8: 直供 | I8: 模切 | J8: PP+PET | K8: 吸音棉 | L8: 403032278AA-2 | M8: 400g/㎡ 10mm双组份吸音棉 | N8: 500*163*142 | O8: =BOM!H7 -> 0.5952 | P8: =工序工时!AB8 -> 0.10185185 | Q8: =(O8+P8)*0.08 -> 0.055764148 | R8: =物流包装!F8 -> 0.053794375 | S8: =物流包装!G8 -> 0.0525 | T8: 0 | U8: 0 | V8: 0 | W8: 0.02 | X8: =模检具!V7 -> 0.010619469 | Y8: =SUM(O8:X8) -> 0.88972984 | Z8: 0 | AA8: 0 | AB8: =Y8+Z8+AA8 -> 0.88972984 | AC8: =0.5*0.163 -> 0.0815 | AD8: 0.4 | AE8: =AB8/AC8/AD8 -> 27.292327
A9: 46266 | B9: T12T | C9: 凯华 | D9: 杨克波 | E9: 芜湖 | F9: 50000 | G9: 5 | H9: 直供 | I9: 模切 | J9: PP+PET | K9: 吸音棉 | L9: 403032287AA-2 | M9: 400g/㎡ 10mm双组份吸音棉 | N9: 500*163*142 | O9: =BOM!H8 -> 0.5952 | P9: =工序工时!AB9 -> 0.10185185 | Q9: =(O9+P9)*0.08 -> 0.055764148 | R9: =物流包装!F9 -> 0.053794375 | S9: =物流包装!G9 -> 0.0525 | T9: 0 | U9: 0 | V9: 0 | W9: 0.02 | X9: =模检具!V8 -> 0.010619469 | Y9: =SUM(O9:X9) -> 0.88972984 | Z9: 0 | AA9: 0 | AB9: =Y9+Z9+AA9 -> 0.88972984 | AC9: =0.5*0.163 -> 0.0815 | AD9: 0.4 | AE9: =AB9/AC9/AD9 -> 27.292327
A10: 46266 | B10: T12T | C10: 凯华 | D10: 杨克波 | E10: 芜湖 | F10: 50000 | G10: 5 | H10: 直供 | I10: 模切 | J10: PET | K10: 毛毡 | L10: 403032278AA-3 | M10: 150g/㎡ 1mmPET毡 带背胶 | N10: 20*20*1 | O10: =BOM!H9 -> 0.05 | P10: =工序工时!AB10 -> 0 | Q10: =(O10+P10)*0.08 -> 0.004 | R10: 0 | S10: 0 | T10: 0 | U10: 0 | V10: 0 | W10: 0.03 | X10: =模检具!V9 -> 0 | Y10: =SUM(O10:X10) -> 0.084 | Z10: 0 | AA10: 0 | AB10: =Y10+Z10+AA10 -> 0.084
A11: 46266 | B11: T12T | C11: 凯华 | D11: 杨克波 | E11: 芜湖 | F11: 50000 | G11: 5 | H11: 直供 | I11: 模切 | J11: PET | K11: 毛毡 | L11: 403032287AA-3 | M11: 150g/㎡ 1mmPET毡 带背胶 | N11: 20*20*1 | O11: =BOM!H10 -> 0.05 | P11: =工序工时!AB11 -> 0 | Q11: =(O11+P11)*0.08 -> 0.004 | R11: 0 | S11: 0 | T11: 0 | U11: 0 | V11: 0 | W11: 0.03 | X11: =模检具!V10 -> 0 | Y11: =SUM(O11:X11) -> 0.084 | Z11: 0 | AA11: 0 | AB11: =Y11+Z11+AA11 -> 0.084
A12: 46266 | B12: T12T | C12: 凯华 | D12: 杨克波 | E12: 芜湖 | F12: 50000 | G12: 5 | H12: 直供 | I12: 模切 | J12: PET | K12: 毛毡 | L12: 403032289AA-4 | M12: 150g/㎡ 1mmPET毡 带背胶 | N12: 20*20*1 | O12: =BOM!H11 -> 0.05 | P12: =工序工时!AB12 -> 0 | Q12: =(O12+P12)*0.08 -> 0.004 | R12: 0 | S12: 0 | T12: 0 | U12: 0 | V12: 0 | W12: 0.03 | X12: =模检具!V11 -> 0 | Y12: =SUM(O12:X12) -> 0.084 | Z12: 0 | AA12: 0 | AB12: =Y12+Z12+AA12 -> 0.084
A13: 46266 | B13: T12T | C13: 凯华 | D13: 杨克波 | E13: 芜湖 | F13: 50000 | G13: 5 | H13: 直供 | I13: 模切 | J13: PET | K13: 毛毡 | L13: 403032289AA-4 | M13: 150g/㎡ 1mmPET毡 带背胶 | N13: 20*20*1 | O13: =BOM!H12 -> 0.05 | P13: =工序工时!AB13 -> 0 | Q13: =(O13+P13)*0.08 -> 0.004 | R13: 0 | S13: 0 | T13: 0 | U13: 0 | V13: 0 | W13: 0.03 | X13: =模检具!V12 -> 0 | Y13: =SUM(O13:X13) -> 0.084 | Z13: 0 | AA13: 0 | AB13: =Y13+Z13+AA13 -> 0.084
O15: 外购供应商：南通华阁

Sheet BOM
A1: 名称 | B1: 零件号 | C1: 产品尺寸 | D1: 材料 | E1: 单位 | F1: 用量 | G1: 单价 | H1: 材料成本 | I1: 备注 | J1: 排版
A2: 吸音棉 | B2: 403032281AA-2 | C2: 354*82*10 | D2: MT402, 10MM 双面白色PP纺粘无纺布 双线封边 预估展开尺寸；354*95*10 用量：1.6*0.38/15 | E2: ㎡ | F2: =1.6*0.38/15 -> 0.040533333 | G2: =13.5*0.4 -> 5.4 | H2: =F2*G2 -> 0.21888
A3: 吸音棉 | B3: 403032282AA-2 | C3: 354*82*10 | D3: MT402, 10MM 双面白色PP纺粘无纺布 双线封边 预估展开尺寸；354*95*10 用量：1.6*0.38/15 | E3: ㎡ | F3: =1.6*0.38/15 -> 0.040533333 | G3: =13.5*0.4 -> 5.4 | H3: =F3*G3 -> 0.21888
A4: 吸音棉 | B4: 403034543AA-3 | C4: 403*90*10 | D4: MT402, 10MM 双面白色PP纺粘无纺布 双线封边 预估展开尺寸；403*100*10 用量：1.6*0.43/14 | E4: ㎡ | F4: =1.6*0.43/14 -> 0.049142857 | G4: =13.5*0.4 -> 5.4 | H4: =F4*G4 -> 0.26537143
A5: 吸音棉 | B5: 403037026AA-3 | C5: 403*90*10 | D5: MT402, 10MM 双面白色PP纺粘无纺布 双线封边 预估展开尺寸；403*100*10 用量：1.6*0.43/14 | E5: ㎡ | F5: =1.6*0.43/14 -> 0.049142857 | G5: =13.5*0.4 -> 5.4 | H5: =F5*G5 -> 0.26537143
A6: 吸音棉 | B6: 403037030AA-3 | C6: 403*90*10 | D6: MT402, 10MM 双面白色PP纺粘无纺布 双线封边 预估展开尺寸；403*100*10 用量：1.6*0.43/14 | E6: ㎡ | F6: =1.6*0.43/14 -> 0.049142857 | G6: =13.5*0.4 -> 5.4 | H6: =F6*G6 -> 0.26537143
A7: 吸音棉 | B7: 403032278AA-2 | C7: 500*163*142 | D7: MT402, 10MM 双面白色PP纺粘无纺布 双线封边 预估展开尺寸；600*163*10 用量：1.6*0.62/9 | E7: ㎡ | F7: =1.6*0.62/9 -> 0.11022222 | G7: =13.5*0.4 -> 5.4 | H7: =F7*G7 -> 0.5952
A8: 吸音棉 | B8: 403032287AA-2 | C8: 500*163*142 | D8: MT402, 10MM 双面白色PP纺粘无纺布 双线封边 预估展开尺寸；600*163*10 用量：1.6*0.62/9 | E8: ㎡ | F8: =1.6*0.62/9 -> 0.11022222 | G8: =13.5*0.4 -> 5.4 | H8: =F7*G7 -> 0.5952
A9: 毛毡 | B9: 403032278AA-3 | C9: 20*20*1 | D9: 150g/㎡ 1mm厚 PET毡 带背胶 | E9: pcs | H9: 0.05 | I9: 外购, 5000起订
A10: 毛毡 | B10: 403032287AA-3 | C10: 20*20*1 | D10: 150g/㎡ 1mm厚 PET毡 带背胶 | E10: pcs | H10: 0.05 | I10: 外购, 5000起订
A11: 毛毡 | B11: 403032289AA-4 | C11: 20*20*1 | D11: 150g/㎡ 1mm厚 PET毡 带背胶 | E11: pcs | H11: 0.05 | I11: 外购, 5000起订
A12: 毛毡 | B12: 403032289AA-4 | C12: 20*20*1 | D12: 150g/㎡ 1mm厚 PET毡 带背胶 | E12: pcs | H12: 0.05 | I12: 外购, 5000起订

Sheet 工序工时
A2: 名称 | B2: 零件号 | D2: 1工序 | E2: 人数 | F2: PCS/（秒） | G2: 2工序 | H2: 人数 | I2: PCS/（秒） | J2: 3工序 | K2: 人数 | L2: PCS/（秒） | M2: 4工序 | N2: 人数 | O2: PCS/（秒） | P2: 5工序 | Q2: 人数 | R2: PCS/（秒） | S2: 6工序 | T2: 人数 | U2: PCS/（秒） | V2: 7工序 | W2: 人数 | X2: PCS/（秒） | Y2: 模切 | Z2: 贴条胶带 | AA2: 检验包装 | AB2: 加工费小计
A3: 吸音棉 | B3: 403032281AA-2 | C3: 15 | D3: 模切 | E3: 1 | F3: =40/C3 -> 2.6666667 | G3: 检验包装 | H3: 1 | I3: =F3 -> 2.6666667 | Y3: =E3*25/3600*F3+60/3600*F3 -> 0.062962963 | AA3: =H3*25/3600*I3 -> 0.018518519 | AB3: =SUM(Y3:AA3) -> 0.081481481
A4: 吸音棉 | B4: 403032282AA-2 | C4: 15 | D4: 模切 | E4: 1 | F4: =40/C4 -> 2.6666667 | G4: 检验包装 | H4: 1 | I4: =F4 -> 2.6666667 | Y4: =E4*25/3600*F4+60/3600*F4 -> 0.062962963 | AA4: =H4*25/3600*I4 -> 0.018518519 | AB4: =SUM(Y4:AA4) -> 0.081481481
A5: 吸音棉 | B5: 403034543AA-3 | C5: 14 | D5: 模切 | E5: 1 | F5: =40/C5 -> 2.8571429 | G5: 检验包装 | H5: 1 | I5: =F5 -> 2.8571429 | Y5: =E5*25/3600*F5+60/3600*F5 -> 0.067460317 | AA5: =H5*25/3600*I5 -> 0.01984127 | AB5: =SUM(Y5:AA5) -> 0.087301587
A6: 吸音棉 | B6: 403037026AA-3 | C6: 14 | D6: 模切 | E6: 1 | F6: =40/C6 -> 2.8571429 | G6: 检验包装 | H6: 1 | I6: =F6 -> 2.8571429 | Y6: =E6*25/3600*F6+60/3600*F6 -> 0.067460317 | AA6: =H6*25/3600*I6 -> 0.01984127 | AB6: =SUM(Y6:AA6) -> 0.087301587
A7: 吸音棉 | B7: 403037030AA-3 | C7: 14 | D7: 模切 | E7: 1 | F7: =40/C7 -> 2.8571429 | G7: 检验包装 | H7: 1 | I7: =F7 -> 2.8571429 | Y7: =E7*25/3600*F7+60/3600*F7 -> 0.067460317 | AA7: =H7*25/3600*I7 -> 0.01984127 | AB7: =SUM(Y7:AA7) -> 0.087301587
A8: 吸音棉 | B8: 403032278AA-2 | C8: 9 | D8: 模切 | E8: 1 | F8: =30/C8 -> 3.3333333 | G8: 检验包装 | H8: 1 | I8: =F8 -> 3.3333333 | Y8: =E8*25/3600*F8+60/3600*F8 -> 0.078703704 | AA8: =H8*25/3600*I8 -> 0.023148148 | AB8: =SUM(Y8:AA8) -> 0.10185185
A9: 吸音棉 | B9: 403032287AA-2 | C9: 9 | D9: 模切 | E9: 1 | F9: =30/C9 -> 3.3333333 | G9: 检验包装 | H9: 1 | I9: =F9 -> 3.3333333 | Y9: =E9*25/3600*F9+60/3600*F9 -> 0.078703704 | AA9: =H9*25/3600*I9 -> 0.023148148 | AB9: =SUM(Y9:AA9) -> 0.10185185
A10: 毛毡 | B10: 403032278AA-3 | D10: 外购
A11: 毛毡 | B11: 403032287AA-3 | D11: 外购
A12: 毛毡 | B12: 403032289AA-4 | D12: 外购
A13: 毛毡 | B13: 403032289AA-4 | D13: 外购

Sheet 模检具
A1: 名称 | B1: 零件号 | C1: 一出N | D1: 刀模数 | E1: 模具1 | F1: 价格 | G1: 模具2 | H1: 价格 | I1: 模具3 | J1: 价格 | K1: 模具4 | L1: 价格 | M1: 模具5 | N1: 价格 | O1: 模具6 | P1: 价格 | Q1: 合计 | R1: 税率 | S1: 未税 | T1: 年量 | U1: 生命周期 | V1: 分摊
A2: 吸音棉 | B2: 403032281AA-2 | C2: 15 | D2: =T2*U2/20000/C2 -> 0.83333333 | E2: 刀模 | F2: 2800 | G2: 检验版 | H2: 200 | Q2: =F2+H2+J2+L2+N2+P2 -> 3000 | R2: 1.13 | S2: =Q2/R2 -> 2654.8673 | T2: =成本!F3 -> 50000 | U2: =成本!G3 -> 5 | V2: =S2/T2/U2 -> 0.010619469
A3: 吸音棉 | B3: 403032282AA-2 | C3: 15 | D3: =T3*U3/20000/C3 -> 0.83333333 | E3: 刀模 | F3: 2800 | G3: 检验版 | H3: 200 | Q3: =F3+H3+J3+L3+N3+P3 -> 3000 | R3: 1.13 | S3: =Q3/R3 -> 2654.8673 | T3: =成本!F4 -> 50000 | U3: =成本!G4 -> 5 | V3: =S3/T3/U3 -> 0.010619469
A4: 吸音棉 | B4: 403034543AA-3 | C4: 14 | D4: =T4*U4/20000/C4 -> 0.89285714 | E4: 刀模 | F4: 2800 | G4: 检验版 | H4: 200 | Q4: =F4+H4+J4+L4+N4+P4 -> 3000 | R4: 1.13 | S4: =Q4/R4 -> 2654.8673 | T4: =成本!F5 -> 50000 | U4: =成本!G5 -> 5 | V4: =S4/T4/U4 -> 0.010619469
A5: 吸音棉 | B5: 403037026AA-3 | C5: 14 | D5: =T5*U5/20000/C5 -> 0.89285714 | E5: 刀模 | F5: 2800 | G5: 检验版 | H5: 200 | Q5: =F5+H5+J5+L5+N5+P5 -> 3000 | R5: 1.13 | S5: =Q5/R5 -> 2654.8673 | T5: =成本!F6 -> 50000 | U5: =成本!G6 -> 5 | V5: =S5/T5/U5 -> 0.010619469
A6: 吸音棉 | B6: 403037030AA-3 | C6: 14 | D6: =T6*U6/20000/C6 -> 0.89285714 | E6: 刀模 | F6: 2800 | G6: 检验版 | H6: 200 | Q6: =F6+H6+J6+L6+N6+P6 -> 3000 | R6: 1.13 | S6: =Q6/R6 -> 2654.8673 | T6: =成本!F7 -> 50000 | U6: =成本!G7 -> 5 | V6: =S6/T6/U6 -> 0.010619469
A7: 吸音棉 | B7: 403032278AA-2 | C7: 9 | D7: =T7*U7/20000/C7 -> 1.3888889 | E7: 刀模 | F7: 2800 | G7: 检验版 | H7: 200 | Q7: =F7+H7+J7+L7+N7+P7 -> 3000 | R7: 1.13 | S7: =Q7/R7 -> 2654.8673 | T7: =成本!F8 -> 50000 | U7: =成本!G8 -> 5 | V7: =S7/T7/U7 -> 0.010619469
A8: 吸音棉 | B8: 403032287AA-2 | C8: 9 | D8: =T8*U8/20000/C8 -> 1.3888889 | E8: 刀模 | F8: 2800 | G8: 检验版 | H8: 200 | Q8: =F8+H8+J8+L8+N8+P8 -> 3000 | R8: 1.13 | S8: =Q8/R8 -> 2654.8673 | T8: =成本!F9 -> 50000 | U8: =成本!G9 -> 5 | V8: =S8/T8/U8 -> 0.010619469
A9: 毛毡 | B9: 403032278AA-3 | C9: 外购件
A10: 毛毡 | B10: 403032287AA-3 | C10: 外购件
A11: 毛毡 | B11: 403032289AA-4 | C11: 外购件
A12: 毛毡 | B12: 403032289AA-4 | C12: 外购件

Sheet 物流包装
T1: 纸箱尺寸
A2: 名称 | B2: 零件号 | C2: 产品尺寸 | D2: 年量纲 | E2: 生命周期 | F2: 运输费 | G2: 包装费 | H2: 托盘费 | I2: 外仓储服务费 | J2: 器具车 | K2: 内包装 | L2: 外包装 | M2: PCS/箱 | N2: 纸箱/层 | O2: 器具车尺寸 | P2: 放置数量 | Q2: 器具数量 | R2: 内包装价格 | S2: 外包装价格 | T2: 长 | U2: 宽 | V2: 高 | W2: 器具车价格 | X2: 目的地 | Y2: 运输费 | Z2: 仓储费 | AA2: 操作费 | AC2: 箱子利用率 | AD2: 产品尺寸
A3: 吸音棉 | B3: 403032281AA-2 | C3: 354*82*10 | D3: 50000 | E3: 5 | F3: =(T3*U3*V3)/10^9*Y3/M3 -> 0.020225625 | G3: =(R3+S3)/M3 -> 0.022916667 | H3: =20/6/P3 -> #DIV/0! | I3: =(T3*U3)/10^6*Z3/M3/3*1.4/4+AA3 -> 0 | J3: =W3/100/P3 -> #DIV/0! | L3: 4# | M3: 240 | R3: 1 | S3: 4.5 | T3: 670 | U3: 460 | V3: 315 | X3: 芜湖 | Y3: 50 | AC3: =AD3*AE3*AF3/T3/U3/V3*M3 -> 0
A4: 吸音棉 | B4: 403032282AA-2 | C4: 354*82*10 | D4: 50000 | E4: 5 | F4: =(T4*U4*V4)/10^9*Y4/M4 -> 0.020225625 | G4: =(R4+S4)/M4 -> 0.022916667 | L4: 4# | M4: 240 | R4: 1 | S4: 4.5 | T4: 670 | U4: 460 | V4: 315 | X4: 芜湖 | Y4: 50
A5: 吸音棉 | B5: 403034543AA-3 | C5: 403*90*10 | D5: 50000 | E5: 5 | F5: =(T5*U5*V5)/10^9*Y5/M5 -> 0.020225625 | G5: =(R5+S5)/M5 -> 0.022916667 | L5: 4# | M5: 240 | R5: 1 | S5: 4.5 | T5: 670 | U5: 460 | V5: 315 | X5: 芜湖 | Y5: 50
A6: 吸音棉 | B6: 403037026AA-3 | C6: 403*90*10 | D6: 50000 | E6: 5 | F6: =(T6*U6*V6)/10^9*Y6/M6 -> 0.020225625 | G6: =(R6+S6)/M6 -> 0.022916667 | L6: 4# | M6: 240 | R6: 1 | S6: 4.5 | T6: 670 | U6: 460 | V6: 315 | X6: 芜湖 | Y6: 50
A7: 吸音棉 | B7: 403037030AA-3 | C7: 403*90*10 | D7: 50000 | E7: 5 | F7: =(T7*U7*V7)/10^9*Y7/M7 -> 0.020225625 | G7: =(R7+S7)/M7 -> 0.022916667 | L7: 4# | M7: 240 | R7: 1 | S7: 4.5 | T7: 670 | U7: 460 | V7: 315 | X7: 芜湖 | Y7: 50
A8: 吸音棉 | B8: 403032278AA-2 | C8: 600*163*10 | D8: 50000 | E8: 5 | F8: =(T8*U8*V8)/10^9*Y8/M8 -> 0.053794375 | G8: =(R8+S8)/M8 -> 0.0525 | L8: 3# | M8: 120 | R8: 1 | S8: 5.3 | T8: 610 | U8: 510 | V8: 415 | X8: 芜湖 | Y8: 50
A9: 吸音棉 | B9: 403032287AA-2 | C9: 600*163*10 | D9: 50000 | E9: 5 | F9: =(T9*U9*V9)/10^9*Y9/M9 -> 0.053794375 | G9: =(R9+S9)/M9 -> 0.0525 | L9: 3# | M9: 120 | R9: 1 | S9: 5.3 | T9: 610 | U9: 510 | V9: 415 | X9: 芜湖 | Y9: 50
A10: 毛毡 | B10: 403032278AA-3 | C10: 20*20*1 | D10: 50000 | E10: 5 | X10: 芜湖
A11: 毛毡 | B11: 403032287AA-3 | C11: 20*20*1 | D11: 50000 | E11: 5 | X11: 芜湖
A12: 毛毡 | B12: 403032289AA-4 | C12: 20*20*1 | D12: 50000 | E12: 5 | X12: 芜湖
A13: 毛毡 | B13: 403032289AA-4 | C13: 20*20*1 | D13: 50000 | E13: 5 | X13: 芜湖

Sheet 实验费
A1: 名称 | B1: 零件号 | C1: 试验报价（含税） | D1: 税率 | E1: 未税价 | F1: 年量 | G1: 生命周期 | H1: 分摊
A2: 吸音棉 | B2: 403032281AA-2 | C2: 30000 | D2: 1.06 | E2: =C2/D2 -> 28301.887 | F2: =成本!F3 -> 50000 | G2: =成本!G3 -> 5 | H2: =E2/F2/G2/7 -> 0.016172507
A3: 吸音棉 | B3: 403032282AA-2
A4: 吸音棉 | B4: 403034543AA-3
A5: 吸音棉 | B5: 403037026AA-3
A6: 吸音棉 | B6: 403037030AA-3
A7: 吸音棉 | B7: 403032278AA-2
A8: 吸音棉 | B8: 403032287AA-2
A9: 毛毡 | B9: 403032278AA-3 | C9: 30000 | D9: 1.06 | E9: =C9/D9 -> 28301.887 | F9: 50000 | G9: 5 | H9: =E9/F9/G9/4 -> 0.028301887
A10: 毛毡 | B10: 403032287AA-3
A11: 毛毡 | B11: 403032289AA-4
A12: 毛毡 | B12: 403032289AA-4
